.DS_Store
fpl_analytics/FPLAnalytics.py
fpl_analytics/FPLUnderStats.py
fpl_analytics/__init__.py
fplanalytics-1.5.0.dist-info/LICENSE
fplanalytics-1.5.0.dist-info/METADATA
fplanalytics-1.5.0.dist-info/WHEEL
fplanalytics-1.5.0.dist-info/top_level.txt
fplanalytics-1.5.0.dist-info/RECORD
